{
	"$schema": "http://schema.management.azure.com/schemas/2015-01-01/deploymentTemplate.json#",
	"contentVersion": "1.0.0.0",
	"parameters": {
		"factoryName": {
			"type": "string",
			"metadata": "Data Factory Name",
			"defaultValue": "7b68d2b5-dfbe-46e1-938f-98ed143b7953"
		},
		"FileServer1_password": {
			"type": "secureString",
			"metadata": "Secure string for 'password' of 'FileServer1'"
		},
		"localfilesystem_password": {
			"type": "secureString",
			"metadata": "Secure string for 'password' of 'localfilesystem'"
		},
		"onpremSqlServer_connectionString": {
			"type": "secureString",
			"metadata": "Secure string for 'connectionString' of 'onpremSqlServer'"
		},
		"FileServer1_properties_typeProperties_userId": {
			"type": "string",
			"defaultValue": "fareast\\abnarain"
		},
		"localfilesystem_properties_typeProperties_userId": {
			"type": "string",
			"defaultValue": "fareast\\abnarain"
		}
	},
	"variables": {
		"factoryId": "[concat('Microsoft.DataFactory/factories/', parameters('factoryName'))]"
	},
	"resources": [
		{
			"name": "[concat(parameters('factoryName'), '/HackCopy_Destination_AzureSqlDWTable_x81')]",
			"type": "Microsoft.DataFactory/factories/datasets",
			"apiVersion": "2018-06-01",
			"properties": {
				"linkedServiceName": {
					"referenceName": "AzureSqlDW1",
					"type": "LinkedServiceReference"
				},
				"annotations": [],
				"type": "AzureSqlDWTable",
				"typeProperties": {
					"tableName": "[concat('[', 'dbo].[Occupation]')]"
				}
			},
			"dependsOn": []
		},
		{
			"name": "[concat(parameters('factoryName'), '/HackCopy_Destination_DocumentDbCollection_1b1')]",
			"type": "Microsoft.DataFactory/factories/datasets",
			"apiVersion": "2018-06-01",
			"properties": {
				"linkedServiceName": {
					"referenceName": "CosmosDb_DBTODOLIST",
					"type": "LinkedServiceReference"
				},
				"annotations": [],
				"type": "DocumentDbCollection",
				"typeProperties": {
					"collectionName": "Product"
				}
			},
			"dependsOn": []
		},
		{
			"name": "[concat(parameters('factoryName'), '/HackCopy_Destination_DocumentDbCollection_47x')]",
			"type": "Microsoft.DataFactory/factories/datasets",
			"apiVersion": "2018-06-01",
			"properties": {
				"linkedServiceName": {
					"referenceName": "CosmosDb_DBTODOLIST",
					"type": "LinkedServiceReference"
				},
				"annotations": [],
				"type": "DocumentDbCollection",
				"typeProperties": {
					"collectionName": "Product"
				}
			},
			"dependsOn": []
		},
		{
			"name": "[concat(parameters('factoryName'), '/HackCopy_Destination_DocumentDbCollection_88d')]",
			"type": "Microsoft.DataFactory/factories/datasets",
			"apiVersion": "2018-06-01",
			"properties": {
				"linkedServiceName": {
					"referenceName": "CosmosDb_DBTODOLIST",
					"type": "LinkedServiceReference"
				},
				"annotations": [],
				"type": "DocumentDbCollection",
				"typeProperties": {
					"collectionName": "Items"
				}
			},
			"dependsOn": []
		},
		{
			"name": "[concat(parameters('factoryName'), '/HackCopy_Destination_DocumentDbCollection_iku')]",
			"type": "Microsoft.DataFactory/factories/datasets",
			"apiVersion": "2018-06-01",
			"properties": {
				"linkedServiceName": {
					"referenceName": "CosmosDb_DBTODOLIST",
					"type": "LinkedServiceReference"
				},
				"annotations": [],
				"type": "DocumentDbCollection",
				"typeProperties": {
					"collectionName": "Items"
				}
			},
			"dependsOn": []
		},
		{
			"name": "[concat(parameters('factoryName'), '/HackCopy_Destination_DocumentDbCollection_ml5')]",
			"type": "Microsoft.DataFactory/factories/datasets",
			"apiVersion": "2018-06-01",
			"properties": {
				"linkedServiceName": {
					"referenceName": "CosmosDb_DBTODOLIST",
					"type": "LinkedServiceReference"
				},
				"annotations": [],
				"type": "DocumentDbCollection",
				"typeProperties": {
					"collectionName": "Items"
				}
			},
			"dependsOn": []
		},
		{
			"name": "[concat(parameters('factoryName'), '/HackCopy_Source_AmazonS3Object_0t1')]",
			"type": "Microsoft.DataFactory/factories/datasets",
			"apiVersion": "2018-06-01",
			"properties": {
				"linkedServiceName": {
					"referenceName": "perf_AmazonS3",
					"type": "LinkedServiceReference"
				},
				"annotations": [],
				"type": "AmazonS3Object",
				"typeProperties": {
					"key": "",
					"prefix": "0001e073-3e00-4758-a3e0-ef360cfc038e/",
					"bucketName": "adfsingapore"
				}
			},
			"dependsOn": []
		},
		{
			"name": "[concat(parameters('factoryName'), '/HackCopy_Source_AmazonS3Object_hn6')]",
			"type": "Microsoft.DataFactory/factories/datasets",
			"apiVersion": "2018-06-01",
			"properties": {
				"linkedServiceName": {
					"referenceName": "perf_AmazonS3",
					"type": "LinkedServiceReference"
				},
				"annotations": [],
				"type": "AmazonS3Object",
				"typeProperties": {
					"key": "",
					"prefix": "tb/sub0/",
					"bucketName": "perf-eastus"
				}
			},
			"dependsOn": []
		},
		{
			"name": "[concat(parameters('factoryName'), '/HackCopy_Source_AmazonS3Object_nhg')]",
			"type": "Microsoft.DataFactory/factories/datasets",
			"apiVersion": "2018-06-01",
			"properties": {
				"linkedServiceName": {
					"referenceName": "perf_AmazonS3",
					"type": "LinkedServiceReference"
				},
				"annotations": [],
				"type": "AmazonS3Object",
				"typeProperties": {
					"key": "",
					"prefix": "tb/sub0/",
					"bucketName": "perf-eastus"
				}
			},
			"dependsOn": []
		},
		{
			"name": "[concat(parameters('factoryName'), '/HackCopy_Source_AmazonS3Object_p07')]",
			"type": "Microsoft.DataFactory/factories/datasets",
			"apiVersion": "2018-06-01",
			"properties": {
				"linkedServiceName": {
					"referenceName": "perf_AmazonS3",
					"type": "LinkedServiceReference"
				},
				"annotations": [],
				"type": "AmazonS3Object",
				"typeProperties": {
					"key": "",
					"prefix": "amazons3.donottouch/",
					"bucketName": "adfcopye2etest"
				}
			},
			"dependsOn": []
		},
		{
			"name": "[concat(parameters('factoryName'), '/HackCopy_Source_AmazonS3Object_tzx')]",
			"type": "Microsoft.DataFactory/factories/datasets",
			"apiVersion": "2018-06-01",
			"properties": {
				"linkedServiceName": {
					"referenceName": "perf_AmazonS3",
					"type": "LinkedServiceReference"
				},
				"annotations": [],
				"type": "AmazonS3Object",
				"typeProperties": {
					"key": "",
					"prefix": "tb/sub0/",
					"bucketName": "perf-eastus"
				}
			},
			"dependsOn": []
		},
		{
			"name": "[concat(parameters('factoryName'), '/HackCopy_Source_AzureSqlDWTable_ml5')]",
			"type": "Microsoft.DataFactory/factories/datasets",
			"apiVersion": "2018-06-01",
			"properties": {
				"linkedServiceName": {
					"referenceName": "AzureSqlDW3",
					"type": "LinkedServiceReference"
				},
				"annotations": [],
				"type": "AzureSqlDWTable",
				"typeProperties": {
					"tableName": "[concat('[', 'dbo].[Product]')]"
				}
			},
			"dependsOn": []
		},
		{
			"name": "[concat(parameters('factoryName'), '/FileServer1')]",
			"type": "Microsoft.DataFactory/factories/linkedServices",
			"apiVersion": "2018-06-01",
			"properties": {
				"annotations": [],
				"type": "FileServer",
				"typeProperties": {
					"host": "\\\\ab-desktop\\data",
					"userId": "[parameters('FileServer1_properties_typeProperties_userId')]",
					"password": {
						"type": "SecureString",
						"value": "[parameters('FileServer1_password')]"
					}
				},
				"connectVia": {
					"referenceName": "[parameters('integrationRuntime_IRForCopyDataTool')]",
					"type": "IntegrationRuntimeReference"
				}
			},
			"dependsOn": []
		},
		{
			"name": "[concat(parameters('factoryName'), '/localfilesystem')]",
			"type": "Microsoft.DataFactory/factories/linkedServices",
			"apiVersion": "2018-06-01",
			"properties": {
				"annotations": [],
				"type": "FileServer",
				"typeProperties": {
					"host": "\\\\ab-desktop\\DB backup",
					"userId": "[parameters('localfilesystem_properties_typeProperties_userId')]",
					"password": {
						"type": "SecureString",
						"value": "[parameters('localfilesystem_password')]"
					}
				},
				"connectVia": {
					"referenceName": "[parameters('integrationRuntime_IRForCopyDataTool')]",
					"type": "IntegrationRuntimeReference"
				}
			},
			"dependsOn": []
		},
		{
			"name": "[concat(parameters('factoryName'), '/onpremSqlServer')]",
			"type": "Microsoft.DataFactory/factories/linkedServices",
			"apiVersion": "2018-06-01",
			"properties": {
				"annotations": [],
				"type": "SqlServer",
				"typeProperties": {
					"connectionString": "[parameters('onpremSqlServer_connectionString')]"
				},
				"connectVia": {
					"referenceName": "[parameters('integrationRuntime_IRForCopyDataTool')]",
					"type": "IntegrationRuntimeReference"
				}
			},
			"dependsOn": []
		},
		{
			"name": "[concat(parameters('factoryName'), '/HackCopy_Pipeline_0t1')]",
			"type": "Microsoft.DataFactory/factories/pipelines",
			"apiVersion": "2018-06-01",
			"properties": {
				"description": "adfsingapore/0001e073-3e00-4758-a3e0-ef360cfc038e/ (perf_AmazonS3) → openhackdemo/ (AzureStorage)",
				"activities": [
					{
						"name": "HackCopy_Copy_0t1",
						"type": "Copy",
						"dependsOn": [],
						"policy": {
							"timeout": "7.00:00:00",
							"retry": 0,
							"retryIntervalInSeconds": 30,
							"secureOutput": false
						},
						"userProperties": [
							{
								"name": "Source",
								"value": "adfsingapore/0001e073-3e00-4758-a3e0-ef360cfc038e/"
							},
							{
								"name": "Destination",
								"value": "openhackdemo/"
							}
						],
						"typeProperties": {
							"source": {
								"type": "FileSystemSource",
								"recursive": true
							},
							"sink": {
								"type": "BlobSink"
							},
							"enableStaging": false,
							"enableSkipIncompatibleRow": true,
							"dataIntegrationUnits": 16
						},
						"inputs": [
							{
								"referenceName": "HackCopy_Source_AmazonS3Object_0t1",
								"type": "DatasetReference",
								"parameters": {}
							}
						],
						"outputs": [
							{
								"referenceName": "HackCopy_Destination_AzureBlob_0t1",
								"type": "DatasetReference",
								"parameters": {}
							}
						]
					}
				],
				"annotations": []
			},
			"dependsOn": [
				"[concat(variables('factoryId'), '/datasets/HackCopy_Source_AmazonS3Object_0t1')]"
			]
		},
		{
			"name": "[concat(parameters('factoryName'), '/HackCopy_Pipeline_hn6')]",
			"type": "Microsoft.DataFactory/factories/pipelines",
			"apiVersion": "2018-06-01",
			"properties": {
				"description": "perf-eastus/tb/sub0/ (perf_AmazonS3) → source/ (AzureStorage1)",
				"activities": [
					{
						"name": "HackCopy_Copy_hn6",
						"type": "Copy",
						"dependsOn": [],
						"policy": {
							"timeout": "7.00:00:00",
							"retry": 0,
							"retryIntervalInSeconds": 30,
							"secureOutput": false
						},
						"userProperties": [
							{
								"name": "Source",
								"value": "perf-eastus/tb/sub0/"
							},
							{
								"name": "Destination",
								"value": "source/"
							}
						],
						"typeProperties": {
							"source": {
								"type": "FileSystemSource",
								"recursive": true
							},
							"sink": {
								"type": "BlobSink"
							},
							"enableStaging": false,
							"enableSkipIncompatibleRow": true,
							"dataIntegrationUnits": 16
						},
						"inputs": [
							{
								"referenceName": "HackCopy_Source_AmazonS3Object_hn6",
								"type": "DatasetReference",
								"parameters": {}
							}
						],
						"outputs": [
							{
								"referenceName": "HackCopy_Destination_AzureBlob_hn6",
								"type": "DatasetReference",
								"parameters": {}
							}
						]
					}
				],
				"annotations": []
			},
			"dependsOn": [
				"[concat(variables('factoryId'), '/datasets/HackCopy_Source_AmazonS3Object_hn6')]"
			]
		},
		{
			"name": "[concat(parameters('factoryName'), '/HackCopy_Pipeline_ml5')]",
			"type": "Microsoft.DataFactory/factories/pipelines",
			"apiVersion": "2018-06-01",
			"properties": {
				"description": "[concat('[', 'dbo].[Product] (AzureSqlDW3) → Items (CosmosDb_DBTODOLIST)')]",
				"activities": [
					{
						"name": "HackCopy_Copy_ml5",
						"type": "Copy",
						"dependsOn": [],
						"policy": {
							"timeout": "7.00:00:00",
							"retry": 0,
							"retryIntervalInSeconds": 30,
							"secureOutput": false
						},
						"userProperties": [
							{
								"name": "Source",
								"value": "[concat('[', 'dbo].[Product]')]"
							},
							{
								"name": "Destination",
								"value": "Items"
							}
						],
						"typeProperties": {
							"source": {
								"type": "SqlDWSource"
							},
							"sink": {
								"type": "DocumentDbCollectionSink",
								"nestingSeparator": ".",
								"writeBatchSize": 10000,
								"writeBehavior": "insert"
							},
							"enableStaging": false,
							"enableSkipIncompatibleRow": true,
							"dataIntegrationUnits": 0
						},
						"inputs": [
							{
								"referenceName": "HackCopy_Source_AzureSqlDWTable_ml5",
								"type": "DatasetReference",
								"parameters": {}
							}
						],
						"outputs": [
							{
								"referenceName": "HackCopy_Destination_DocumentDbCollection_ml5",
								"type": "DatasetReference",
								"parameters": {}
							}
						]
					}
				],
				"annotations": []
			},
			"dependsOn": [
				"[concat(variables('factoryId'), '/datasets/HackCopy_Source_AzureSqlDWTable_ml5')]",
				"[concat(variables('factoryId'), '/datasets/HackCopy_Destination_DocumentDbCollection_ml5')]"
			]
		},
		{
			"name": "[concat(parameters('factoryName'), '/HackCopy_Pipeline_nhg')]",
			"type": "Microsoft.DataFactory/factories/pipelines",
			"apiVersion": "2018-06-01",
			"properties": {
				"description": "perf-eastus/tb/sub0/ (perf_AmazonS3) → perf/hybriddatamover/ (AzureStorage)",
				"activities": [
					{
						"name": "HackCopy_Copy_nhg",
						"type": "Copy",
						"dependsOn": [],
						"policy": {
							"timeout": "7.00:00:00",
							"retry": 0,
							"retryIntervalInSeconds": 30,
							"secureOutput": false
						},
						"userProperties": [
							{
								"name": "Source",
								"value": "perf-eastus/tb/sub0/"
							},
							{
								"name": "Destination",
								"value": "perf/hybriddatamover/"
							}
						],
						"typeProperties": {
							"source": {
								"type": "FileSystemSource",
								"recursive": true
							},
							"sink": {
								"type": "BlobSink"
							},
							"enableStaging": false,
							"enableSkipIncompatibleRow": true,
							"dataIntegrationUnits": 16
						},
						"inputs": [
							{
								"referenceName": "HackCopy_Source_AmazonS3Object_nhg",
								"type": "DatasetReference",
								"parameters": {}
							}
						],
						"outputs": [
							{
								"referenceName": "HackCopy_Destination_AzureBlob_nhg",
								"type": "DatasetReference",
								"parameters": {}
							}
						]
					}
				],
				"annotations": []
			},
			"dependsOn": [
				"[concat(variables('factoryId'), '/datasets/HackCopy_Source_AmazonS3Object_nhg')]"
			]
		},
		{
			"name": "[concat(parameters('factoryName'), '/HackCopy_Pipeline_p07')]",
			"type": "Microsoft.DataFactory/factories/pipelines",
			"apiVersion": "2018-06-01",
			"properties": {
				"description": "adfcopye2etest/amazons3.donottouch/ (perf_AmazonS3) → adfjobs/ (AzureStorage)",
				"activities": [
					{
						"name": "HackCopy_Copy_p07",
						"type": "Copy",
						"dependsOn": [],
						"policy": {
							"timeout": "7.00:00:00",
							"retry": 0,
							"retryIntervalInSeconds": 30,
							"secureOutput": false
						},
						"userProperties": [
							{
								"name": "Source",
								"value": "adfcopye2etest/amazons3.donottouch/"
							},
							{
								"name": "Destination",
								"value": "adfjobs/"
							}
						],
						"typeProperties": {
							"source": {
								"type": "FileSystemSource",
								"recursive": true
							},
							"sink": {
								"type": "BlobSink"
							},
							"enableStaging": false,
							"enableSkipIncompatibleRow": true,
							"dataIntegrationUnits": 16
						},
						"inputs": [
							{
								"referenceName": "HackCopy_Source_AmazonS3Object_p07",
								"type": "DatasetReference",
								"parameters": {}
							}
						],
						"outputs": [
							{
								"referenceName": "HackCopy_Destination_AzureBlob_p07",
								"type": "DatasetReference",
								"parameters": {}
							}
						]
					}
				],
				"annotations": []
			},
			"dependsOn": [
				"[concat(variables('factoryId'), '/datasets/HackCopy_Source_AmazonS3Object_p07')]"
			]
		}
	]
}